neuralspace/__init__.py
neuralspace/constants.py
neuralspace/env.py
neuralspace/utils.py
neuralspace/version.py
neuralspace/voice_ai.py
voice_ai-0.0.2.dist-info/METADATA
voice_ai-0.0.2.dist-info/WHEEL
voice_ai-0.0.2.dist-info/top_level.txt
voice_ai-0.0.2.dist-info/RECORD
