Metadata-Version: 2.1
Name: voice-ai
Version: 0.0.2
Classifier: Programming Language :: Python :: 3
Requires-Python: >=3.7
Requires-Dist: requests
Requires-Dist: websocket-client
